nogan_synthesizer/__init__.py
nogan_synthesizer/nogan_synthesizer.py
nogan_synthesizer/preprocessing.py
nogan_synthesizer-0.1.5.dist-info/LICENSE
nogan_synthesizer-0.1.5.dist-info/METADATA
nogan_synthesizer-0.1.5.dist-info/WHEEL
nogan_synthesizer-0.1.5.dist-info/top_level.txt
nogan_synthesizer-0.1.5.dist-info/RECORD
