Metadata-Version: 2.1
Name: nogan_synthesizer
Version: 0.1.5
Summary: NoGAN Tabular Synthetic Data Generation
Home-page: https://github.com/rajiviyer/nogan_synthesizer
Author: Rajiv Iyer
Author-email: raju.rgi@gmail.com
License: MIT license
Keywords: nogan_synthesizer
Classifier: Development Status :: 2 - Pre-Alpha
Classifier: Intended Audience :: Developers
Classifier: License :: OSI Approved :: MIT License
Classifier: Natural Language :: English
Classifier: Programming Language :: Python :: 3
Classifier: Programming Language :: Python :: 3.6
Classifier: Programming Language :: Python :: 3.7
Classifier: Programming Language :: Python :: 3.8
Requires-Python: >=3.6
License-File: LICENSE
